wish/__init__.py
wish/client.py
wish/notification.py
wish/oauth.py
wish/order.py
wish/product.py
wish/resource.py
wish/settings.py
wish/shipping.py
wish/ticket.py
wish/utils.py
wish/variation.py
wish_api-1.0.1.dist-info/DESCRIPTION.rst
wish_api-1.0.1.dist-info/METADATA
wish_api-1.0.1.dist-info/RECORD
wish_api-1.0.1.dist-info/WHEEL
wish_api-1.0.1.dist-info/metadata.json
wish_api-1.0.1.dist-info/top_level.txt
