Metadata-Version: 2.0
Name: wish-api
Version: 1.0.1
Summary: simple python wish partner api client
Home-page: https://github.com/ketu/wish_api
Author: ketu.lai
Author-email: ketu.lai@gmail.com
License: MIT
Keywords: wish api
Platform: UNKNOWN
